sentaku/__init__.py
sentaku/chooser.py
sentaku/context.py
sentaku/modeling.py
sentaku/py.typed
sentaku-0.9.1.dist-info/METADATA
sentaku-0.9.1.dist-info/WHEEL
sentaku-0.9.1.dist-info/licenses/LICENSE.rst
sentaku-0.9.1.dist-info/RECORD
