Metadata-Version: 2.1
Name: sentaku
Version: 0.9.1
Summary: variadic ux implementation for testing
Project-URL: Homepage, https://github.com/Redhatqe/Sentaku
Author-email: RonnyPfannschmidt <opensource@ronnypfannschmidt.de>
License-Expression: MPL-2.0
License-File: LICENSE.rst
Keywords: testing
Classifier: Development Status :: 4 - Beta
Classifier: Intended Audience :: Developers
Classifier: License :: OSI Approved :: Mozilla Public License 2.0 (MPL 2.0)
Classifier: Programming Language :: Python :: 3.6
Classifier: Programming Language :: Python :: 3.7
Classifier: Programming Language :: Python :: 3.8
Classifier: Programming Language :: Python :: 3.9
Classifier: Programming Language :: Python :: 3.10
Classifier: Topic :: Software Development :: Libraries :: Python Modules
Classifier: Topic :: Utilities
Requires-Python: >=3.8
Requires-Dist: attrs>=22
Requires-Dist: typing-extensions>=4.5
Provides-Extra: docs
Requires-Dist: requests>=2.20; extra == 'docs'
Requires-Dist: selenium>=4; extra == 'docs'
Requires-Dist: sphinx>=6.1.3; extra == 'docs'
Provides-Extra: examples
Requires-Dist: selenium>=4; extra == 'examples'
Provides-Extra: test
Requires-Dist: pytest>7.1; extra == 'test'
